<?xml version="1.0" encoding="UTF-8"?>
<?xml-model href="dplava.xsd" type="application/xml" schematypens="http://purl.oclc.org/dsdl/schematron"?>
<mdRecord xmlns="http://dplava.lib.virginia.edu" xmlns:xsi="http://www.w3.org/2001/XMLSchema-instance" xmlns:dc="http://purl.org/dc/elements/1.1/" xmlns:dcterms="http://purl.org/dc/terms/" xmlns:rdf="http://www.w3.org/1999/02/22-rdf-syntax-ns#" xmlns:edm="http://www.europeana.eu/schemas/edm/" xsi:schemaLocation="http://dplava.lib.virginia.edu/dplava.xsd">
<dcterms:rights>http://rightsstatements.org/vocab/UND/1.0/</dcterms:rights>
<dcterms:provenance>College of William &amp; Mary</dcterms:provenance>
<dcterms:medium>nonprojected graphic</dcterms:medium>
<dcterms:created>1815-09-05</dcterms:created>
<edm:isShownAt>http://hdl.handle.net/10288/15267</edm:isShownAt>
<dcterms:description>Write Madison concerning constitution he has written; Jefferson deposited copy in Library of Congress which was then destroyed by fire; sends 6 additional copies of constitution, three of which he asks to be deposted in Library of Congress; hopes constitution will be printed in Spanish to send to Mexico and colonies as well as in French to stop bloodshed in Santo Domingo.</dcterms:description>
<dcterms:language>eng</dcterms:language>
<dcterms:subject>Jefferson, Thomas, 1743-1826--Correspondence</dcterms:subject>
<dcterms:title>Letter, 1815 September 5, Paris, [France] to [James] Madison, n.p.</dcterms:title>
<dcterms:type>text</dcterms:type>
<dcterms:identifier>Mss. 40 T79</dcterms:identifier>
<dcterms:isPartOf>Tucker-Coleman Papers</dcterms:isPartOf>
<edm:preview>https://digitalarchive.wm.edu/rest/bitstreams/e219a35e-3e3f-47d8-8b5e-20d14b76daea/retrieve</edm:preview>
</mdRecord>
