<?xml version="1.0" encoding="UTF-8"?>
<?xml-model href="dplava.xsd" type="application/xml" schematypens="http://purl.oclc.org/dsdl/schematron"?>
<mdRecord xmlns="http://dplava.lib.virginia.edu" xmlns:xsi="http://www.w3.org/2001/XMLSchema-instance" xmlns:dc="http://purl.org/dc/elements/1.1/" xmlns:dcterms="http://purl.org/dc/terms/" xmlns:rdf="http://www.w3.org/1999/02/22-rdf-syntax-ns#" xmlns:edm="http://www.europeana.eu/schemas/edm/" xsi:schemaLocation="http://dplava.lib.virginia.edu/dplava.xsd">
<dcterms:rights>http://rightsstatements.org/vocab/UND/1.0/</dcterms:rights>
<dcterms:provenance>College of William &amp; Mary</dcterms:provenance>
<dcterms:medium>nonprojected graphic</dcterms:medium>
<dcterms:creator>Ferguson, Robert Crauford</dcterms:creator>
<dcterms:created>1804-05-19</dcterms:created>
<edm:isShownAt>https://hdl.handle.net/10288/22650</edm:isShownAt>
<dcterms:description>Sir Robert Crauford Ferguson, Conduit St., London, England, to Alexander Munro, Bedford Square, London, England. Requests him to get information about his RCF brother, a prisoner of war in France, from James Monroe, the American Minister. 1 page. Autograph letter signed.</dcterms:description>
<dcterms:language>eng</dcterms:language>
<dcterms:isPartOf>Monroe Family Papers</dcterms:isPartOf>
<dcterms:title>Sir Robert Crauford Ferguson to Alexander Munro, May 19, 1804</dcterms:title>
<dcterms:type>Text</dcterms:type>
<dcterms:identifier>Mss. 82 M75</dcterms:identifier>
<edm:preview>https://digitalarchive.wm.edu/rest/bitstreams/b95604a8-ccf1-4a26-abee-48bbc73dabfc/retrieve</edm:preview>
</mdRecord>
